[{"company":"Tanoodle","position":"Business Systems Development Analyst","jobLocation":"Timbó","jobStatus":"interview","jobType":"full-time","createdAt":"2/2/2023"},
{"company":"Shuffledrive","position":"Geological Engineer","jobLocation":"Trasak","jobStatus":"declined","jobType":"full-time","createdAt":"5/25/2023"},
{"company":"Photofeed","position":"Registered Nurse","jobLocation":"Mouquim","jobStatus":"interview","jobType":"full-time","createdAt":"3/4/2023"},
{"company":"Gigabox","position":"Help Desk Operator","jobLocation":"Quebradas","jobStatus":"interview","jobType":"part-time","createdAt":"4/2/2023"},
{"company":"Skidoo","position":"Electrical Engineer","jobLocation":"Lembanah","jobStatus":"pending","jobType":"internship","createdAt":"1/11/2023"},
{"company":"Fliptune","position":"Legal Assistant","jobLocation":"Dan Sadau","jobStatus":"interview","jobType":"internship","createdAt":"4/1/2023"},
{"company":"Kimia","position":"Technical Writer","jobLocation":"Viso","jobStatus":"pending","jobType":"part-time","createdAt":"1/1/2023"},
{"company":"Gabspot","position":"Nurse Practicioner","jobLocation":"Kabīrwāla","jobStatus":"interview","jobType":"full-time","createdAt":"5/8/2023"},
{"company":"Skinder","position":"VP Marketing","jobLocation":"Semiluki","jobStatus":"interview","jobType":"part-time","createdAt":"12/31/2022"},
{"company":"Tagcat","position":"Nurse","jobLocation":"Chengbei","jobStatus":"pending","jobType":"full-time","createdAt":"11/7/2022"},
{"company":"Flipstorm","position":"Senior Sales Associate","jobLocation":"Chantilly","jobStatus":"declined","jobType":"part-time","createdAt":"1/13/2023"},
{"company":"Thoughtworks","position":"VP Sales","jobLocation":"Lincoln","jobStatus":"declined","jobType":"part-time","createdAt":"11/17/2022"},
{"company":"Vitz","position":"Product Engineer","jobLocation":"Sibulan","jobStatus":"interview","jobType":"part-time","createdAt":"12/18/2022"},
{"company":"Viva","position":"Systems Administrator III","jobLocation":"Buray","jobStatus":"declined","jobType":"full-time","createdAt":"5/20/2023"},
{"company":"Skajo","position":"VP Marketing","jobLocation":"Nueva Vida Sur","jobStatus":"pending","jobType":"full-time","createdAt":"3/31/2023"},
{"company":"Realcube","position":"Operator","jobLocation":"Halmstad","jobStatus":"interview","jobType":"full-time","createdAt":"1/29/2023"},
{"company":"Cogilith","position":"Account Coordinator","jobLocation":"Judaydah","jobStatus":"interview","jobType":"part-time","createdAt":"12/22/2022"},
{"company":"Linkbuzz","position":"Structural Engineer","jobLocation":"Huolianpo","jobStatus":"pending","jobType":"full-time","createdAt":"2/24/2023"},
{"company":"Yakitri","position":"Environmental Specialist","jobLocation":"Dobrovo","jobStatus":"interview","jobType":"part-time","createdAt":"11/3/2022"},
{"company":"Skinder","position":"Programmer III","jobLocation":"San Sebastián","jobStatus":"declined","jobType":"part-time","createdAt":"2/15/2023"},
{"company":"Jazzy","position":"Environmental Specialist","jobLocation":"Uddevalla","jobStatus":"pending","jobType":"full-time","createdAt":"11/16/2022"},
{"company":"Abatz","position":"Assistant Professor","jobLocation":"Qiucun","jobStatus":"declined","jobType":"part-time","createdAt":"5/15/2023"},
{"company":"Kazu","position":"Environmental Specialist","jobLocation":"Nerchinsk","jobStatus":"pending","jobType":"full-time","createdAt":"2/13/2023"},
{"company":"Pixope","position":"Nurse","jobLocation":"Nagqu","jobStatus":"declined","jobType":"full-time","createdAt":"12/20/2022"},
{"company":"Yacero","position":"Biostatistician IV","jobLocation":"Clermont-Ferrand","jobStatus":"interview","jobType":"part-time","createdAt":"1/2/2023"},
{"company":"Brightdog","position":"Systems Administrator III","jobLocation":"Sairam","jobStatus":"interview","jobType":"part-time","createdAt":"3/2/2023"},
{"company":"Quimba","position":"Cost Accountant","jobLocation":"Zhushan","jobStatus":"declined","jobType":"part-time","createdAt":"2/18/2023"},
{"company":"Mita","position":"Information Systems Manager","jobLocation":"Rāipur","jobStatus":"interview","jobType":"part-time","createdAt":"3/17/2023"},
{"company":"Gigabox","position":"Structural Analysis Engineer","jobLocation":"Oakland","jobStatus":"declined","jobType":"part-time","createdAt":"11/20/2022"},
{"company":"Chatterbridge","position":"Analog Circuit Design manager","jobLocation":"Bilice","jobStatus":"declined","jobType":"internship","createdAt":"3/1/2023"},
{"company":"Zoombox","position":"Clinical Specialist","jobLocation":"Dinskaya","jobStatus":"pending","jobType":"internship","createdAt":"3/1/2023"},
{"company":"Brightbean","position":"Assistant Media Planner","jobLocation":"Guadalupe","jobStatus":"interview","jobType":"full-time","createdAt":"2/7/2023"},
{"company":"Skivee","position":"Financial Analyst","jobLocation":"Kuala Lumpur","jobStatus":"declined","jobType":"internship","createdAt":"11/20/2022"},
{"company":"Realcube","position":"Technical Writer","jobLocation":"Sámara","jobStatus":"declined","jobType":"full-time","createdAt":"12/9/2022"},
{"company":"Quaxo","position":"Marketing Assistant","jobLocation":"Sławatycze","jobStatus":"declined","jobType":"part-time","createdAt":"12/4/2022"},
{"company":"Linkbridge","position":"Quality Control Specialist","jobLocation":"Saint-Lambert-de-Lauzon","jobStatus":"pending","jobType":"full-time","createdAt":"4/17/2023"},
{"company":"Rooxo","position":"Quality Engineer","jobLocation":"Timbrangan","jobStatus":"declined","jobType":"internship","createdAt":"6/1/2023"},
{"company":"Rhyzio","position":"Desktop Support Technician","jobLocation":"Huangnaihai","jobStatus":"pending","jobType":"full-time","createdAt":"5/5/2023"},
{"company":"Voomm","position":"Physical Therapy Assistant","jobLocation":"Liwu","jobStatus":"pending","jobType":"full-time","createdAt":"12/8/2022"},
{"company":"Realbuzz","position":"Legal Assistant","jobLocation":"Nova Friburgo","jobStatus":"interview","jobType":"full-time","createdAt":"1/30/2023"},
{"company":"Zava","position":"General Manager","jobLocation":"Mandi Bahāuddīn","jobStatus":"declined","jobType":"part-time","createdAt":"4/18/2023"},
{"company":"Zazio","position":"Quality Control Specialist","jobLocation":"Batugede Kulon","jobStatus":"declined","jobType":"full-time","createdAt":"2/21/2023"},
{"company":"Feedbug","position":"Structural Analysis Engineer","jobLocation":"Affery","jobStatus":"interview","jobType":"part-time","createdAt":"11/12/2022"},
{"company":"Twitterlist","position":"Research Nurse","jobLocation":"Duotian","jobStatus":"pending","jobType":"full-time","createdAt":"2/22/2023"},
{"company":"Skibox","position":"Research Nurse","jobLocation":"Majāz al Bāb","jobStatus":"interview","jobType":"full-time","createdAt":"4/5/2023"},
{"company":"Meemm","position":"Graphic Designer","jobLocation":"Agkathiá","jobStatus":"interview","jobType":"internship","createdAt":"11/3/2022"},
{"company":"Jazzy","position":"Safety Technician I","jobLocation":"Shicheng","jobStatus":"declined","jobType":"part-time","createdAt":"5/27/2023"},
{"company":"Reallinks","position":"Account Executive","jobLocation":"Ujazd","jobStatus":"pending","jobType":"full-time","createdAt":"2/26/2023"},
{"company":"Edgeblab","position":"Environmental Tech","jobLocation":"Ivry-sur-Seine","jobStatus":"pending","jobType":"part-time","createdAt":"1/4/2023"},
{"company":"Meeveo","position":"Financial Analyst","jobLocation":"Qorveh","jobStatus":"declined","jobType":"internship","createdAt":"3/28/2023"},
{"company":"Riffwire","position":"Staff Accountant I","jobLocation":"Ilembula","jobStatus":"declined","jobType":"internship","createdAt":"5/13/2023"},
{"company":"Izio","position":"Junior Executive","jobLocation":"Shiye","jobStatus":"interview","jobType":"internship","createdAt":"3/19/2023"},
{"company":"Photobug","position":"Recruiting Manager","jobLocation":"Nekla","jobStatus":"pending","jobType":"internship","createdAt":"2/25/2023"},
{"company":"Jayo","position":"Assistant Manager","jobLocation":"Monte Carmelo","jobStatus":"interview","jobType":"part-time","createdAt":"2/20/2023"},
{"company":"Dynabox","position":"Research Assistant II","jobLocation":"Nanaimo","jobStatus":"pending","jobType":"internship","createdAt":"1/22/2023"},
{"company":"Topicblab","position":"Senior Developer","jobLocation":"Robīt","jobStatus":"declined","jobType":"internship","createdAt":"1/8/2023"},
{"company":"Edgeify","position":"Software Consultant","jobLocation":"Tanjungjaya","jobStatus":"pending","jobType":"part-time","createdAt":"1/8/2023"},
{"company":"Brightdog","position":"Design Engineer","jobLocation":"Sidi Moussa","jobStatus":"interview","jobType":"full-time","createdAt":"2/27/2023"},
{"company":"Dabtype","position":"Environmental Specialist","jobLocation":"Rostock","jobStatus":"interview","jobType":"internship","createdAt":"11/28/2022"},
{"company":"Buzzster","position":"Compensation Analyst","jobLocation":"Trąbki Wielkie","jobStatus":"declined","jobType":"part-time","createdAt":"3/26/2023"},
{"company":"Tavu","position":"Accounting Assistant I","jobLocation":"Gagah","jobStatus":"declined","jobType":"part-time","createdAt":"4/2/2023"},
{"company":"Babbleopia","position":"Staff Accountant III","jobLocation":"Huangjing","jobStatus":"declined","jobType":"full-time","createdAt":"6/1/2023"},
{"company":"Photobug","position":"Human Resources Assistant II","jobLocation":"Al Maḩjal","jobStatus":"pending","jobType":"full-time","createdAt":"5/16/2023"},
{"company":"Riffpath","position":"Quality Engineer","jobLocation":"Dornava","jobStatus":"declined","jobType":"full-time","createdAt":"1/18/2023"},
{"company":"Topicblab","position":"Physical Therapy Assistant","jobLocation":"Moluo","jobStatus":"declined","jobType":"part-time","createdAt":"4/26/2023"},
{"company":"Meemm","position":"Nuclear Power Engineer","jobLocation":"Bayt Ūlā","jobStatus":"interview","jobType":"internship","createdAt":"12/20/2022"},
{"company":"Agimba","position":"Nuclear Power Engineer","jobLocation":"Budziszewice","jobStatus":"interview","jobType":"internship","createdAt":"3/29/2023"},
{"company":"Leenti","position":"Account Coordinator","jobLocation":"Spitsevka","jobStatus":"interview","jobType":"part-time","createdAt":"5/9/2023"},
{"company":"Dynabox","position":"Computer Systems Analyst II","jobLocation":"Kramsk","jobStatus":"pending","jobType":"part-time","createdAt":"4/8/2023"},
{"company":"Livetube","position":"Teacher","jobLocation":"Luoqi","jobStatus":"interview","jobType":"part-time","createdAt":"11/12/2022"},
{"company":"Skibox","position":"Marketing Assistant","jobLocation":"Goiatuba","jobStatus":"pending","jobType":"part-time","createdAt":"5/25/2023"},
{"company":"Realfire","position":"Director of Sales","jobLocation":"Campoalegre","jobStatus":"declined","jobType":"internship","createdAt":"4/22/2023"},
{"company":"Dabtype","position":"Account Coordinator","jobLocation":"Saḩab","jobStatus":"pending","jobType":"full-time","createdAt":"3/9/2023"},
{"company":"Ainyx","position":"VP Marketing","jobLocation":"Cilangkap","jobStatus":"pending","jobType":"full-time","createdAt":"2/9/2023"},
{"company":"Browsedrive","position":"VP Sales","jobLocation":"Dārān","jobStatus":"declined","jobType":"full-time","createdAt":"11/18/2022"},
{"company":"Linkbridge","position":"Assistant Manager","jobLocation":"Kedian","jobStatus":"declined","jobType":"full-time","createdAt":"4/21/2023"},
{"company":"Devify","position":"Data Coordinator","jobLocation":"Viengxay","jobStatus":"pending","jobType":"internship","createdAt":"1/25/2023"},
{"company":"Vinder","position":"Media Manager II","jobLocation":"Nytva","jobStatus":"declined","jobType":"full-time","createdAt":"12/22/2022"},
{"company":"Digitube","position":"Librarian","jobLocation":"Shanghu","jobStatus":"interview","jobType":"part-time","createdAt":"12/20/2022"},
{"company":"Demivee","position":"Senior Developer","jobLocation":"Manizales","jobStatus":"declined","jobType":"full-time","createdAt":"3/21/2023"},
{"company":"Twimbo","position":"Senior Quality Engineer","jobLocation":"Kurumkan","jobStatus":"interview","jobType":"full-time","createdAt":"4/15/2023"},
{"company":"Voonix","position":"Analog Circuit Design manager","jobLocation":"Krajan","jobStatus":"interview","jobType":"full-time","createdAt":"11/11/2022"},
{"company":"Divape","position":"Operator","jobLocation":"Mengyin","jobStatus":"declined","jobType":"full-time","createdAt":"5/16/2023"},
{"company":"Jabberstorm","position":"Financial Analyst","jobLocation":"Lelystad","jobStatus":"pending","jobType":"internship","createdAt":"2/9/2023"},
{"company":"Buzzshare","position":"Social Worker","jobLocation":"Piribebuy","jobStatus":"interview","jobType":"full-time","createdAt":"5/12/2023"},
{"company":"Viva","position":"Accounting Assistant III","jobLocation":"Cola","jobStatus":"interview","jobType":"full-time","createdAt":"4/7/2023"},
{"company":"Roomm","position":"Chief Design Engineer","jobLocation":"Piteå","jobStatus":"declined","jobType":"part-time","createdAt":"4/1/2023"},
{"company":"Tavu","position":"Database Administrator IV","jobLocation":"Liangbing","jobStatus":"interview","jobType":"full-time","createdAt":"4/18/2023"},
{"company":"Gabtune","position":"VP Sales","jobLocation":"Correia Pinto","jobStatus":"declined","jobType":"part-time","createdAt":"5/17/2023"},
{"company":"Meezzy","position":"Food Chemist","jobLocation":"Orsha","jobStatus":"pending","jobType":"part-time","createdAt":"2/4/2023"},
{"company":"Centizu","position":"Graphic Designer","jobLocation":"Malishka","jobStatus":"interview","jobType":"internship","createdAt":"4/6/2023"},
{"company":"Zoovu","position":"Geologist III","jobLocation":"Ulbroka","jobStatus":"declined","jobType":"internship","createdAt":"5/1/2023"},
{"company":"Edgeclub","position":"Editor","jobLocation":"Coxim","jobStatus":"pending","jobType":"full-time","createdAt":"4/18/2023"},
{"company":"Jaloo","position":"Civil Engineer","jobLocation":"Timaru","jobStatus":"declined","jobType":"internship","createdAt":"3/23/2023"},
{"company":"Tanoodle","position":"Executive Secretary","jobLocation":"Boden","jobStatus":"declined","jobType":"internship","createdAt":"1/4/2023"},
{"company":"Aimbu","position":"Speech Pathologist","jobLocation":"Suidong","jobStatus":"pending","jobType":"full-time","createdAt":"12/14/2022"},
{"company":"Voonte","position":"Senior Cost Accountant","jobLocation":"Cicayur","jobStatus":"pending","jobType":"internship","createdAt":"12/27/2022"},
{"company":"Geba","position":"Nuclear Power Engineer","jobLocation":"Casa Branca","jobStatus":"interview","jobType":"part-time","createdAt":"3/3/2023"},
{"company":"Blogtags","position":"Geological Engineer","jobLocation":"Kuala Terengganu","jobStatus":"declined","jobType":"full-time","createdAt":"1/8/2023"},
{"company":"Eimbee","position":"Director of Sales","jobLocation":"Gamping Lor","jobStatus":"pending","jobType":"part-time","createdAt":"4/21/2023"}]